{
"defaultWidth": 170,
"defaultHeight": 60,
"left": 13,
"margin": 10,
"buttonRows": [
    {
        "top": 60,
        "width": 170,
        "buttons": [
            {
                "display": "Tag Name",
                "paste": "AutoShutdownSchedule"
            },
            {
                "display": "Tag Value",
                "paste": "4pm -> 7am"
            }
        ]
    }
    ,{
        "top": 100,
        "width": 170,
        "buttons": [
            {
                "display": "Tag Name",
                "paste": "4pm -> 7am"
            },
            {
                "display": "Tag Name",
                "paste": "AutoShutdownSchedule"
            }
        ]
    }
    ,{
        "top": 140,
        "width": 170,
        "buttons": [
            {
                "display": "Azure Subscription Label",
                "paste": "Default Azure Subscription"
            },
            {
                "display": "Azure Subscription Value",
                "paste": "VM and Web Apps 3d5fb527"
            }
        ]
    }]

}